pdfriend/__init__.py
pdfriend/main.py
pdfriend/utils.py
pdfriend/classes/__init__.py
pdfriend/classes/cmdparsers.py
pdfriend/classes/config.py
pdfriend/classes/exceptions.py
pdfriend/classes/info.py
pdfriend/classes/platforms.py
pdfriend/classes/shells.py
pdfriend/classes/wrappers.py
pdfriend/commands/__init__.py
pdfriend/commands/cache.py
pdfriend/commands/decrypt.py
pdfriend/commands/edit.py
pdfriend/commands/encrypt.py
pdfriend/commands/get.py
pdfriend/commands/invert.py
pdfriend/commands/merge.py
pdfriend/commands/metadata.py
pdfriend/commands/split.py
pdfriend/commands/subset.py
pdfriend/commands/tinker.py
pdfriend/commands/version.py
pdfriend/commands/weave.py
pdfriend/ops/pages.py
pdfriend/ops/pdf.py
pdfriend-0.9.0.dist-info/licenses/LICENSE
pdfriend-0.9.0.dist-info/METADATA
pdfriend-0.9.0.dist-info/WHEEL
pdfriend-0.9.0.dist-info/entry_points.txt
pdfriend-0.9.0.dist-info/top_level.txt
pdfriend-0.9.0.dist-info/RECORD
