Metadata-Version: 2.4
Name: pdfriend
Version: 0.9.0
Summary: A command line utility for easily modifying PDF files
Author: A. Grigoras
License-Expression: GPL-3.0-or-later
Classifier: Programming Language :: Python :: 3
Classifier: Programming Language :: Python :: 3.11
Classifier: Programming Language :: Python :: 3.12
Classifier: Programming Language :: Python :: 3.13
Classifier: Operating System :: OS Independent
Requires-Python: >=3.11
License-File: LICENSE
Requires-Dist: pypdf>=3.17.3
Requires-Dist: pillow>=10.1.0
Requires-Dist: platformdirs>=4.1.0
Dynamic: license-file
